jj_multi_db_mcp/__init__.py
jj_multi_db_mcp/__main__.py
jj_multi_db_mcp/filesystem.py
jj_multi_db_mcp/mysql_manager.py
jj_multi_db_mcp/oracle_manager.py
jj_multi_db_mcp/redis_manager.py
jj_multi_db_mcp/server.py
jj_multi_db_mcp/sqlserver_manager.py
jj_multi_db_mcp-1.0.1.dist-info/METADATA
jj_multi_db_mcp-1.0.1.dist-info/WHEEL
jj_multi_db_mcp-1.0.1.dist-info/entry_points.txt
jj_multi_db_mcp-1.0.1.dist-info/licenses/LICENSE
jj_multi_db_mcp-1.0.1.dist-info/RECORD
