Metadata-Version: 2.4
Name: jj-multi-db-mcp
Version: 1.0.1
Summary: Multi-database MCP server supporting SQL Server, MySQL, Oracle, Redis and filesystem operations
Project-URL: Homepage, https://github.com/ppengit/jj-multi-db-mcp
Project-URL: Repository, https://github.com/ppengit/jj-multi-db-mcp
Author-email: PJ <peng.it@qq.com>
License: MIT
License-File: LICENSE
Requires-Python: >=3.8
Requires-Dist: mcp>=1.0.0
Provides-Extra: all
Requires-Dist: oracledb>=1.4.0; extra == 'all'
Requires-Dist: pymysql>=1.0.0; extra == 'all'
Requires-Dist: pyodbc>=4.0.0; extra == 'all'
Requires-Dist: redis>=5.0.0; extra == 'all'
Requires-Dist: sqlalchemy>=2.0.0; extra == 'all'
Provides-Extra: mysql
Requires-Dist: pymysql>=1.0.0; extra == 'mysql'
Requires-Dist: sqlalchemy>=2.0.0; extra == 'mysql'
Provides-Extra: oracle
Requires-Dist: oracledb>=1.4.0; extra == 'oracle'
Requires-Dist: sqlalchemy>=2.0.0; extra == 'oracle'
Provides-Extra: redis
Requires-Dist: redis>=5.0.0; extra == 'redis'
Provides-Extra: sqlserver
Requires-Dist: pyodbc>=4.0.0; extra == 'sqlserver'
Requires-Dist: sqlalchemy>=2.0.0; extra == 'sqlserver'
